bitcli/__init__.py
bitcli/bootstrap.py
bitcli/main.py
bitcli/controllers/__init__.py
bitcli/controllers/base.py
bitcli/core/__init__.py
bitcli/core/exc.py
bitcli/core/version.py
bitcli/ext/__init__.py
bitcli/plugins/__init__.py
bitcli/templates/__init__.py
bitcli-1.0.0rc0.dist-info/LICENSE.md
bitcli-1.0.0rc0.dist-info/METADATA
bitcli-1.0.0rc0.dist-info/WHEEL
bitcli-1.0.0rc0.dist-info/entry_points.txt
bitcli-1.0.0rc0.dist-info/top_level.txt
bitcli-1.0.0rc0.dist-info/RECORD
