Metadata-Version: 2.1
Name: bitcli
Version: 1.0.0rc0
Summary: Show prices in the console from Bitpanda
Home-page: https://github.com/jmolinaso/bitcli/
Author: Julio Molina Soler
Author-email: julio@molinasoler.xyz
License: MIT
Platform: UNKNOWN
